pelican/plugins/avatar/__init__.py
pelican/plugins/avatar/avatar.py
pelican/plugins/avatar/test_avatar.py
pelican_avatar-1.0.11.dist-info/METADATA
pelican_avatar-1.0.11.dist-info/WHEEL
pelican_avatar-1.0.11.dist-info/entry_points.txt
pelican_avatar-1.0.11.dist-info/licenses/LICENSE
pelican_avatar-1.0.11.dist-info/RECORD
